strix/__init__.py
strix/base_functions.py
strix/file_actions.py
strix/gca.py
strix/value_validation.py
strix/file_formats/__init__.py
strix/file_formats/csv.py
strix/file_formats/egf.py
strix/file_formats/geo_json.py
strix/file_formats/kml_base.py
strix/file_formats/kml_gca.py
strix-0.7.3.dist-info/LICENSE
strix-0.7.3.dist-info/METADATA
strix-0.7.3.dist-info/WHEEL
strix-0.7.3.dist-info/top_level.txt
strix-0.7.3.dist-info/RECORD
